netarch/__init__.py
netarch/crypto.py
netarch/dumbdecode.py
netarch/hexdump.py
netarch/ip.py
netarch/py_pcap.py
netarch/trilobytes.py
netarch/unpack.py
netarch-1.0.0.dist-info/COPYING.txt
netarch-1.0.0.dist-info/METADATA
netarch-1.0.0.dist-info/WHEEL
netarch-1.0.0.dist-info/top_level.txt
netarch-1.0.0.dist-info/RECORD
