Metadata-Version: 2.1
Name: netarch
Version: 1.0.0
Summary: Network Archaeology toolkit
Home-page: https://github.com/dirtbags/netarch
Author: Neale Pickett
Author-email: neale@woozle.org
License: UNKNOWN
Project-URL: Bug Reports, https://github.com/dirtbags/netarch/issues
Project-URL: Source, https://github.com/dirtbags/netarch/
Keywords: network,packet,tcp,protocol,development
Platform: UNKNOWN
Classifier: Development Status :: 5 - Production/Stable
Classifier: Intended Audience :: Developers
Classifier: License :: Public Domain
Classifier: Programming Language :: Python :: 3 :: Only
Requires-Python: >=3.6, <4
